{
  "worst": {
    "linearity_error_pct": 3.1930965087891647,
    "k_mult": 0.6710697887970617,
    "output_offset_mv": 0,
    "power_uw": 264.69390000000004
  },
  "corners": [
    {
      "k_mult": 1.388686868686869,
      "linearity_error_pct": 1.5587721850452438,
      "output_offset_mv": 0.0,
      "power_uw": 52.73886,
      "corner": "tt",
      "temp": -40,
      "vdd": 1.62,
      "status": "PASS"
    },
    {
      "k_mult": 1.4082093663911845,
      "linearity_error_pct": 1.4403928166203919,
      "output_offset_mv": 0.0,
      "power_uw": 58.61891,
      "corner": "tt",
      "temp": -40,
      "vdd": 1.8,
      "status": "PASS"
    },
    {
      "k_mult": 1.4267392102846637,
      "linearity_error_pct": 1.357105113601589,
      "output_offset_mv": 0.0,
      "power_uw": 64.50853,
      "corner": "tt",
      "temp": -40,
      "vdd": 1.98,
      "status": "PASS"
    },
    {
      "k_mult": 1.1792415059687784,
      "linearity_error_pct": 2.664862162570436,
      "output_offset_mv": 0.0,
      "power_uw": 112.71130000000001,
      "corner": "tt",
      "temp": 27,
      "vdd": 1.62,
      "status": "PASS"
    },
    {
      "k_mult": 1.2003645546372823,
      "linearity_error_pct": 2.6077171229738862,
      "output_offset_mv": 0.0,
      "power_uw": 125.3827,
      "corner": "tt",
      "temp": 27,
      "vdd": 1.8,
      "status": "PASS"
    },
    {
      "k_mult": 1.2190064279155195,
      "linearity_error_pct": 2.5607571536829967,
      "output_offset_mv": 0.0,
      "power_uw": 138.073,
      "corner": "tt",
      "temp": 27,
      "vdd": 1.98,
      "status": "PASS"
    },
    {
      "k_mult": 0.7012323232323237,
      "linearity_error_pct": 1.478493849212002,
      "output_offset_mv": 0.0,
      "power_uw": 170.17010000000002,
      "corner": "tt",
      "temp": 175,
      "vdd": 1.62,
      "status": "PASS"
    },
    {
      "k_mult": 0.7229595959595961,
      "linearity_error_pct": 1.4348986349601882,
      "output_offset_mv": 0.0,
      "power_uw": 189.66750000000002,
      "corner": "tt",
      "temp": 175,
      "vdd": 1.8,
      "status": "PASS"
    },
    {
      "k_mult": 0.7390128558310383,
      "linearity_error_pct": 1.4115571239522866,
      "output_offset_mv": 0.0,
      "power_uw": 209.19830000000002,
      "corner": "tt",
      "temp": 175,
      "vdd": 1.98,
      "status": "PASS"
    },
    {
      "k_mult": 1.0778769513314967,
      "linearity_error_pct": 0.9932799912763794,
      "output_offset_mv": 0.0,
      "power_uw": 32.266220000000004,
      "corner": "ss",
      "temp": -40,
      "vdd": 1.62,
      "status": "PASS"
    },
    {
      "k_mult": 1.091282828282828,
      "linearity_error_pct": 0.876366430019371,
      "output_offset_mv": 0.0,
      "power_uw": 35.86287,
      "corner": "ss",
      "temp": -40,
      "vdd": 1.8,
      "status": "PASS"
    },
    {
      "k_mult": 1.1041735537190083,
      "linearity_error_pct": 0.7794951120425576,
      "output_offset_mv": 0.0,
      "power_uw": 39.46861,
      "corner": "ss",
      "temp": -40,
      "vdd": 1.98,
      "status": "PASS"
    },
    {
      "k_mult": 1.0794058769513315,
      "linearity_error_pct": 2.3917180573266643,
      "output_offset_mv": 0.0,
      "power_uw": 78.87863,
      "corner": "ss",
      "temp": 27,
      "vdd": 1.62,
      "status": "PASS"
    },
    {
      "k_mult": 1.094804407713498,
      "linearity_error_pct": 2.3318252502428543,
      "output_offset_mv": 0.0,
      "power_uw": 87.70407,
      "corner": "ss",
      "temp": 27,
      "vdd": 1.8,
      "status": "PASS"
    },
    {
      "k_mult": 1.1088907254361808,
      "linearity_error_pct": 2.284399734345262,
      "output_offset_mv": 0.0,
      "power_uw": 96.54085,
      "corner": "ss",
      "temp": 27,
      "vdd": 1.98,
      "status": "PASS"
    },
    {
      "k_mult": 0.6760261707988977,
      "linearity_error_pct": 1.3685279325721045,
      "output_offset_mv": 0.0,
      "power_uw": 139.51670000000001,
      "corner": "ss",
      "temp": 175,
      "vdd": 1.62,
      "status": "PASS"
    },
    {
      "k_mult": 0.6901019283746553,
      "linearity_error_pct": 1.3376871704184359,
      "output_offset_mv": 0.0,
      "power_uw": 155.4236,
      "corner": "ss",
      "temp": 175,
      "vdd": 1.8,
      "status": "PASS"
    },
    {
      "k_mult": 0.7013921028466484,
      "linearity_error_pct": 1.32230799040608,
      "output_offset_mv": 0.0,
      "power_uw": 171.3671,
      "corner": "ss",
      "temp": 175,
      "vdd": 1.98,
      "status": "PASS"
    },
    {
      "k_mult": 1.6296437098255288,
      "linearity_error_pct": 2.783202849862597,
      "output_offset_mv": 0.0,
      "power_uw": 83.94521,
      "corner": "ff",
      "temp": -40,
      "vdd": 1.62,
      "status": "PASS"
    },
    {
      "k_mult": 1.6573452708907241,
      "linearity_error_pct": 2.640719528337376,
      "output_offset_mv": 0.0,
      "power_uw": 93.31511,
      "corner": "ff",
      "temp": -40,
      "vdd": 1.8,
      "status": "PASS"
    },
    {
      "k_mult": 1.6828328741965113,
      "linearity_error_pct": 2.505722728029106,
      "output_offset_mv": 0.0,
      "power_uw": 102.6943,
      "corner": "ff",
      "temp": -40,
      "vdd": 1.98,
      "status": "PASS"
    },
    {
      "k_mult": 1.214238200183655,
      "linearity_error_pct": 2.8985361475495814,
      "output_offset_mv": 0.0,
      "power_uw": 153.9279,
      "corner": "ff",
      "temp": 27,
      "vdd": 1.62,
      "status": "PASS"
    },
    {
      "k_mult": 1.244943985307622,
      "linearity_error_pct": 2.8337208204499436,
      "output_offset_mv": 0.0,
      "power_uw": 171.3731,
      "corner": "ff",
      "temp": 27,
      "vdd": 1.8,
      "status": "PASS"
    },
    {
      "k_mult": 1.2702699724517899,
      "linearity_error_pct": 2.7865489212937966,
      "output_offset_mv": 0.0,
      "power_uw": 188.8528,
      "corner": "ff",
      "temp": 27,
      "vdd": 1.98,
      "status": "PASS"
    },
    {
      "k_mult": 0.693979981634527,
      "linearity_error_pct": 1.6375779000355237,
      "output_offset_mv": 0.0,
      "power_uw": 203.898,
      "corner": "ff",
      "temp": 175,
      "vdd": 1.62,
      "status": "PASS"
    },
    {
      "k_mult": 0.7329196510560145,
      "linearity_error_pct": 1.5618377258896878,
      "output_offset_mv": 0.0,
      "power_uw": 227.45219999999998,
      "corner": "ff",
      "temp": 175,
      "vdd": 1.8,
      "status": "PASS"
    },
    {
      "k_mult": 0.7577125803489434,
      "linearity_error_pct": 1.5189983869579369,
      "output_offset_mv": 0.0,
      "power_uw": 251.0031,
      "corner": "ff",
      "temp": 175,
      "vdd": 1.98,
      "status": "PASS"
    },
    {
      "k_mult": 1.6636556473829194,
      "linearity_error_pct": 3.1930965087891647,
      "output_offset_mv": 0.0,
      "power_uw": 100.0528,
      "corner": "sf",
      "temp": -40,
      "vdd": 1.62,
      "status": "PASS"
    },
    {
      "k_mult": 1.693832874196511,
      "linearity_error_pct": 3.0667077238012146,
      "output_offset_mv": 0.0,
      "power_uw": 111.2296,
      "corner": "sf",
      "temp": -40,
      "vdd": 1.8,
      "status": "PASS"
    },
    {
      "k_mult": 1.7213057851239668,
      "linearity_error_pct": 2.951557266943378,
      "output_offset_mv": 0.0,
      "power_uw": 122.41619999999999,
      "corner": "sf",
      "temp": -40,
      "vdd": 1.98,
      "status": "PASS"
    },
    {
      "k_mult": 1.1922675849403126,
      "linearity_error_pct": 2.988625666735009,
      "output_offset_mv": 0.0,
      "power_uw": 170.1275,
      "corner": "sf",
      "temp": 27,
      "vdd": 1.62,
      "status": "PASS"
    },
    {
      "k_mult": 1.2272901744719922,
      "linearity_error_pct": 2.9096481232215816,
      "output_offset_mv": 0.0,
      "power_uw": 189.46800000000002,
      "corner": "sf",
      "temp": 27,
      "vdd": 1.8,
      "status": "PASS"
    },
    {
      "k_mult": 1.2549770431588607,
      "linearity_error_pct": 2.8615539962097807,
      "output_offset_mv": 0.0,
      "power_uw": 208.8469,
      "corner": "sf",
      "temp": 27,
      "vdd": 1.98,
      "status": "PASS"
    },
    {
      "k_mult": 0.6714030303030305,
      "linearity_error_pct": 1.7041052281592304,
      "output_offset_mv": 0.0,
      "power_uw": 214.9179,
      "corner": "sf",
      "temp": 175,
      "vdd": 1.62,
      "status": "PASS"
    },
    {
      "k_mult": 0.719788429752066,
      "linearity_error_pct": 1.6101047956138672,
      "output_offset_mv": 0.0,
      "power_uw": 239.8254,
      "corner": "sf",
      "temp": 175,
      "vdd": 1.8,
      "status": "PASS"
    },
    {
      "k_mult": 0.7483627180899904,
      "linearity_error_pct": 1.5550322896510798,
      "output_offset_mv": 0.0,
      "power_uw": 264.69390000000004,
      "corner": "sf",
      "temp": 175,
      "vdd": 1.98,
      "status": "PASS"
    },
    {
      "k_mult": 0.9553911845730026,
      "linearity_error_pct": 1.041117009364592,
      "output_offset_mv": 0.0,
      "power_uw": 26.16466,
      "corner": "fs",
      "temp": -40,
      "vdd": 1.62,
      "status": "PASS"
    },
    {
      "k_mult": 0.9667603305785128,
      "linearity_error_pct": 1.2854268893866307,
      "output_offset_mv": 0.0,
      "power_uw": 29.08124,
      "corner": "fs",
      "temp": -40,
      "vdd": 1.8,
      "status": "PASS"
    },
    {
      "k_mult": 0.977790633608816,
      "linearity_error_pct": 1.512658548817008,
      "output_offset_mv": 0.0,
      "power_uw": 32.00623,
      "corner": "fs",
      "temp": -40,
      "vdd": 1.98,
      "status": "PASS"
    },
    {
      "k_mult": 1.0384738292011018,
      "linearity_error_pct": 2.2226584537243625,
      "output_offset_mv": 0.0,
      "power_uw": 68.03399,
      "corner": "fs",
      "temp": 27,
      "vdd": 1.62,
      "status": "PASS"
    },
    {
      "k_mult": 1.052200183654729,
      "linearity_error_pct": 2.156310708419635,
      "output_offset_mv": 0.0,
      "power_uw": 75.63737,
      "corner": "fs",
      "temp": 27,
      "vdd": 1.8,
      "status": "PASS"
    },
    {
      "k_mult": 1.0649191919191918,
      "linearity_error_pct": 2.104773919394305,
      "output_offset_mv": 0.0,
      "power_uw": 83.25101,
      "corner": "fs",
      "temp": 27,
      "vdd": 1.98,
      "status": "PASS"
    },
    {
      "k_mult": 0.6710697887970617,
      "linearity_error_pct": 1.3307425474994863,
      "output_offset_mv": 0.0,
      "power_uw": 129.94469999999998,
      "corner": "fs",
      "temp": 175,
      "vdd": 1.62,
      "status": "PASS"
    },
    {
      "k_mult": 0.683564738292012,
      "linearity_error_pct": 1.299029287938606,
      "output_offset_mv": 0.0,
      "power_uw": 144.73839999999998,
      "corner": "fs",
      "temp": 175,
      "vdd": 1.8,
      "status": "PASS"
    },
    {
      "k_mult": 0.6937456382001834,
      "linearity_error_pct": 1.285922098137744,
      "output_offset_mv": 0.0,
      "power_uw": 159.5672,
      "corner": "fs",
      "temp": 175,
      "vdd": 1.98,
      "status": "PASS"
    }
  ]
}